pulse2percept/__init__.py
pulse2percept/percepts/__init__.py
pulse2percept/percepts/base.py
pulse2percept/percepts/tests/__init__.py
pulse2percept/percepts/tests/test_base.py
pulse2percept/datasets/nanduri2012.py
pulse2percept/datasets/han2021.py
pulse2percept/datasets/__init__.py
pulse2percept/datasets/horsager2009.py
pulse2percept/datasets/beyeler2019.py
pulse2percept/datasets/perezfornos2012.py
pulse2percept/datasets/greenwald2009.py
pulse2percept/datasets/base.py
pulse2percept/datasets/tests/test_nanduri2012.py
pulse2percept/datasets/tests/test_horsager2009.py
pulse2percept/datasets/tests/__init__.py
pulse2percept/datasets/tests/test_perezfornos2012.py
pulse2percept/datasets/tests/test_han2021.py
pulse2percept/datasets/tests/test_greenwald2009.py
pulse2percept/datasets/tests/test_base.py
pulse2percept/datasets/tests/test_beyeler2019.py
pulse2percept/datasets/data/perez-fornos-2012.csv
pulse2percept/datasets/data/nanduri2012.csv
pulse2percept/datasets/data/greenwald2009.csv
pulse2percept/datasets/data/horsager2009.csv
pulse2percept/utils/optimize.py
pulse2percept/utils/convolution.py
pulse2percept/utils/deprecation.py
pulse2percept/utils/constants.py
pulse2percept/utils/__init__.py
pulse2percept/utils/_fast_array.cpython-310-darwin.so
pulse2percept/utils/_fast_math.cpython-310-darwin.so
pulse2percept/utils/stats.py
pulse2percept/utils/geometry.py
pulse2percept/utils/images.py
pulse2percept/utils/three_dim.py
pulse2percept/utils/parallel.py
pulse2percept/utils/testing.py
pulse2percept/utils/array.py
pulse2percept/utils/base.py
pulse2percept/utils/tests/test_three_dim.py
pulse2percept/utils/tests/test_deprecation.py
pulse2percept/utils/tests/test_stats.py
pulse2percept/utils/tests/test_images.py
pulse2percept/utils/tests/test_optimize.py
pulse2percept/utils/tests/test_array.py
pulse2percept/utils/tests/test_convolution.py
pulse2percept/utils/tests/__init__.py
pulse2percept/utils/tests/test_parallel.py
pulse2percept-0.9.0.dist-info/RECORD
pulse2percept-0.9.0.dist-info/LICENSE
pulse2percept-0.9.0.dist-info/AUTHORS
pulse2percept-0.9.0.dist-info/WHEEL
pulse2percept-0.9.0.dist-info/top_level.txt
pulse2percept-0.9.0.dist-info/METADATA
