Metadata-Version: 2.2
Name: pulse2percept
Version: 0.9.0
Summary: A Python-based simulation framework for bionic vision
Author-email: Michael Beyeler <mbeyeler@ucsb.edu>, Jacob Granley <jgranley@ucsb.edu>, Apurv Varshney <apurv@ucsb.edu>, Ariel Rokem <arokem@gmail.com>
License: Copyright (c) 2016-2020, the pulse2percept developers
Keywords: bionic vision,simulation,scientific computing
Classifier: Programming Language :: Python :: 3
Classifier: License :: OSI Approved :: BSD License
Classifier: Operating System :: OS Independent
Requires-Python: >=3.9
License-File: LICENSE
License-File: AUTHORS
Requires-Dist: cython>=0.28
Requires-Dist: numpy<1.27,>=1.21
Requires-Dist: scipy<=1.7.1; python_version < "3.10"
Requires-Dist: scipy>=1.0.1; python_version >= "3.10"
Requires-Dist: scikit-image>=0.14
Requires-Dist: matplotlib>=3.0.2
Requires-Dist: imageio-ffmpeg>=0.4
Requires-Dist: pandas
Requires-Dist: joblib>=0.11
Provides-Extra: dev
Requires-Dist: dask; extra == "dev"
Requires-Dist: h5py; extra == "dev"
Requires-Dist: pytest>=5; extra == "dev"
Requires-Dist: pytest-cov; extra == "dev"
Requires-Dist: coveralls; extra == "dev"
Requires-Dist: flake8; extra == "dev"
Requires-Dist: mock; extra == "dev"
Requires-Dist: black; extra == "dev"
Requires-Dist: tox; extra == "dev"
Requires-Dist: seaborn; extra == "dev"
Requires-Dist: pyswarm; extra == "dev"
Requires-Dist: scikit-learn; extra == "dev"
Requires-Dist: neuropythy; extra == "dev"
